{
  "feature_index": 0,
  "threshold": 590,
  "info_gain": 0.14990569272976684,
  "value": null,
  "left": {
    "feature_index": 0,
    "threshold": 545,
    "info_gain": 0.3326822916666667,
    "value": null,
    "left": {
      "feature_index": 0,
      "threshold": 446,
      "info_gain": 0.36531986531986527,
      "value": null,
      "left": {
        "feature_index": null,
        "threshold": null,
        "info_gain": null,
        "value": 0,
        "left": null,
        "right": null
      },
      "right": {
        "feature_index": 0,
        "threshold": 465,
        "info_gain": 0.4628099173553719,
        "value": null,
        "left": {
          "feature_index": null,
          "threshold": null,
          "info_gain": null,
          "value": 1,
          "left": null,
          "right": null
        },
        "right": {
          "feature_index": null,
          "threshold": null,
          "info_gain": null,
          "value": 2,
          "left": null,
          "right": null
        }
      }
    },
    "right": {
      "feature_index": null,
      "threshold": null,
      "info_gain": null,
      "value": 3,
      "left": null,
      "right": null
    }
  },
  "right": {
    "feature_index": 0,
    "threshold": 640,
    "info_gain": 0.2540106951871658,
    "value": null,
    "left": {
      "feature_index": null,
      "threshold": null,
      "info_gain": null,
      "value": 4,
      "left": null,
      "right": null
    },
    "right": {
      "feature_index": 0,
      "threshold": 684,
      "info_gain": 0.38556599110232337,
      "value": null,
      "left": {
        "feature_index": null,
        "threshold": null,
        "info_gain": null,
        "value": 5,
        "left": null,
        "right": null
      },
      "right": {
        "feature_index": 0,
        "threshold": 745,
        "info_gain": 0.40816326530612246,
        "value": null,
        "left": {
          "feature_index": null,
          "threshold": null,
          "info_gain": null,
          "value": 6,
          "left": null,
          "right": null
        },
        "right": {
          "feature_index": null,
          "threshold": null,
          "info_gain": null,
          "value": 7,
          "left": null,
          "right": null
        }
      }
    }
  }
}